Django_ConfPages-0.1.1.dist-info/DESCRIPTION.rst
Django_ConfPages-0.1.1.dist-info/METADATA
Django_ConfPages-0.1.1.dist-info/RECORD
Django_ConfPages-0.1.1.dist-info/WHEEL
Django_ConfPages-0.1.1.dist-info/metadata.json
Django_ConfPages-0.1.1.dist-info/top_level.txt
confpages/__init__.py
confpages/conf.py
confpages/loaders.py
confpages/token.py
confpages/urls.py
confpages/utils.py
confpages/views.py
confpages/contrib/__init__.py
confpages/contrib/loaders.py
confpages/templatetags/__init__.py
confpages/templatetags/confpages_tags.py
confpages/tests/__init__.py
confpages/tests/loaders.py
confpages/tests/settings.py
confpages/tests/tests.py
confpages/tests/urls.py
