Metadata-Version: 2.0
Name: Django-ConfPages
Version: 0.1.1
Summary: A Django app for serving configurable pages.
Home-page: https://github.com/RussellLuo/django-confpages
Author: RussellLuo
Author-email: luopeng.he@gmail.com
License: MIT
Keywords: Configurable Pages,Django,Python
Platform: UNKNOWN
Requires-Dist: django (>=1.4)
Requires-Dist: python-easyconfig (==0.1.5)
Requires-Dist: requests (>=2.5.0)
